llama_index/embeddings/azure_openai/__init__.py
llama_index/embeddings/azure_openai/base.py
llama_index_embeddings_azure_openai-0.4.1.dist-info/METADATA
llama_index_embeddings_azure_openai-0.4.1.dist-info/WHEEL
llama_index_embeddings_azure_openai-0.4.1.dist-info/licenses/LICENSE
llama_index_embeddings_azure_openai-0.4.1.dist-info/RECORD
